{
  "year": 2018,
  "scope": "state_house",
  "contest_type": "lieutenant_governor",
  "meta": {
    "match_coverage_pct": 98.25,
    "matched_precinct_keys": 954,
    "total_precinct_keys": 971,
    "weighted_vote_coverage_pct": 98.31,
    "source": "idaho_hybrid_precinct_crosswalk_population_weighted",
    "office": "Lieutenant Governor",
    "nongeo_allocation_mode": "precinct_population_weighted",
    "candidate_count": 2,
    "precinct_basis_breakdown": {
      "modern_2020_vtd20_rows": 173,
      "legacy_2008_vtd00_rows": 171,
      "direct_2022_districtcoded_rows": 610
    }
  },
  "general": {
    "results": {
      "1": {
        "dem_votes": 6658,
        "rep_votes": 12413,
        "other_votes": 0,
        "total_votes": 19071,
        "dem_candidate": "Kristin Collum",
        "rep_candidate": "Janice McGeachin",
        "margin": 5755,
        "margin_pct": 30.1767,
        "winner": "REP",
        "color": "#a50f15",
        "competitiveness": {
          "color": "#a50f15"
        },
        "no_data": false
      },
      "2": {
        "dem_votes": 11632,
        "rep_votes": 22594,
        "other_votes": 0,
        "total_votes": 34227,
        "dem_candidate": "Kristin Collum",
        "rep_candidate": "Janice McGeachin",
        "margin": 10962,
        "margin_pct": 32.0273,
        "winner": "REP",
        "color": "#a50f15",
        "competitiveness": {
          "color": "#a50f15"
        },
        "no_data": false
      },
      "3": {
        "dem_votes": 1957,
        "rep_votes": 6471,
        "other_votes": 0,
        "total_votes": 8428,
        "dem_candidate": "Kristin Collum",
        "rep_candidate": "Janice McGeachin",
        "margin": 4514,
        "margin_pct": 53.5596,
        "winner": "REP",
        "color": "#a50f15",
        "competitiveness": {
          "color": "#a50f15"
        },
        "no_data": false
      },
      "4": {
        "dem_votes": 5004,
        "rep_votes": 8907,
        "other_votes": 0,
        "total_votes": 13911,
        "dem_candidate": "Kristin Collum",
        "rep_candidate": "Janice McGeachin",
        "margin": 3903,
        "margin_pct": 28.0569,
        "winner": "REP",
        "color": "#de2d26",
        "competitiveness": {
          "color": "#de2d26"
        },
        "no_data": false
      },
      "5": {
        "dem_votes": 3056,
        "rep_votes": 7744,
        "other_votes": 0,
        "total_votes": 10800,
        "dem_candidate": "Kristin Collum",
        "rep_candidate": "Janice McGeachin",
        "margin": 4688,
        "margin_pct": 43.4074,
        "winner": "REP",
        "color": "#a50f15",
        "competitiveness": {
          "color": "#a50f15"
        },
        "no_data": false
      },
      "6": {
        "dem_votes": 10557,
        "rep_votes": 9612,
        "other_votes": 0,
        "total_votes": 20169,
        "dem_candidate": "Kristin Collum",
        "rep_candidate": "Janice McGeachin",
        "margin": -945,
        "margin_pct": -4.6854,
        "winner": "DEM",
        "color": "#cbd5e1",
        "competitiveness": {
          "color": "#cbd5e1"
        },
        "no_data": false
      },
      "7": {
        "dem_votes": 4998,
        "rep_votes": 11719,
        "other_votes": 0,
        "total_votes": 16717,
        "dem_candidate": "Kristin Collum",
        "rep_candidate": "Janice McGeachin",
        "margin": 6721,
        "margin_pct": 40.2046,
        "winner": "REP",
        "color": "#a50f15",
        "competitiveness": {
          "color": "#a50f15"
        },
        "no_data": false
      },
      "8": {
        "dem_votes": 6314,
        "rep_votes": 11329,
        "other_votes": 0,
        "total_votes": 17643,
        "dem_candidate": "Kristin Collum",
        "rep_candidate": "Janice McGeachin",
        "margin": 5015,
        "margin_pct": 28.4249,
        "winner": "REP",
        "color": "#de2d26",
        "competitiveness": {
          "color": "#de2d26"
        },
        "no_data": false
      },
      "9": {
        "dem_votes": 5700,
        "rep_votes": 13190,
        "other_votes": 0,
        "total_votes": 18889,
        "dem_candidate": "Kristin Collum",
        "rep_candidate": "Janice McGeachin",
        "margin": 7490,
        "margin_pct": 39.6527,
        "winner": "REP",
        "color": "#a50f15",
        "competitiveness": {
          "color": "#a50f15"
        },
        "no_data": false
      },
      "10": {
        "dem_votes": 2321,
        "rep_votes": 2025,
        "other_votes": 0,
        "total_votes": 4347,
        "dem_candidate": "Kristin Collum",
        "rep_candidate": "Janice McGeachin",
        "margin": -296,
        "margin_pct": -6.8093,
        "winner": "DEM",
        "color": "#6baed6",
        "competitiveness": {
          "color": "#6baed6"
        },
        "no_data": false
      },
      "11": {
        "dem_votes": 3021,
        "rep_votes": 3769,
        "other_votes": 0,
        "total_votes": 6790,
        "dem_candidate": "Kristin Collum",
        "rep_candidate": "Janice McGeachin",
        "margin": 748,
        "margin_pct": 11.0162,
        "winner": "REP",
        "color": "#fb6a4a",
        "competitiveness": {
          "color": "#fb6a4a"
        },
        "no_data": false
      },
      "12": {
        "dem_votes": 2832,
        "rep_votes": 4368,
        "other_votes": 0,
        "total_votes": 7200,
        "dem_candidate": "Kristin Collum",
        "rep_candidate": "Janice McGeachin",
        "margin": 1536,
        "margin_pct": 21.3333,
        "winner": "REP",
        "color": "#de2d26",
        "competitiveness": {
          "color": "#de2d26"
        },
        "no_data": false
      },
      "13": {
        "dem_votes": 7230,
        "rep_votes": 12050,
        "other_votes": 0,
        "total_votes": 19279,
        "dem_candidate": "Kristin Collum",
        "rep_candidate": "Janice McGeachin",
        "margin": 4820,
        "margin_pct": 25.0013,
        "winner": "REP",
        "color": "#de2d26",
        "competitiveness": {
          "color": "#de2d26"
        },
        "no_data": false
      },
      "14": {
        "dem_votes": 11302,
        "rep_votes": 16583,
        "other_votes": 0,
        "total_votes": 27885,
        "dem_candidate": "Kristin Collum",
        "rep_candidate": "Janice McGeachin",
        "margin": 5281,
        "margin_pct": 18.9385,
        "winner": "REP",
        "color": "#fb6a4a",
        "competitiveness": {
          "color": "#fb6a4a"
        },
        "no_data": false
      },
      "15": {
        "dem_votes": 9283,
        "rep_votes": 8744,
        "other_votes": 0,
        "total_votes": 18027,
        "dem_candidate": "Kristin Collum",
        "rep_candidate": "Janice McGeachin",
        "margin": -539,
        "margin_pct": -2.99,
        "winner": "DEM",
        "color": "#cbd5e1",
        "competitiveness": {
          "color": "#cbd5e1"
        },
        "no_data": false
      },
      "16": {
        "dem_votes": 9341,
        "rep_votes": 7207,
        "other_votes": 0,
        "total_votes": 16548,
        "dem_candidate": "Kristin Collum",
        "rep_candidate": "Janice McGeachin",
        "margin": -2134,
        "margin_pct": -12.8958,
        "winner": "DEM",
        "color": "#2171b5",
        "competitiveness": {
          "color": "#2171b5"
        },
        "no_data": false
      },
      "17": {
        "dem_votes": 10568,
        "rep_votes": 5392,
        "other_votes": 0,
        "total_votes": 15960,
        "dem_candidate": "Kristin Collum",
        "rep_candidate": "Janice McGeachin",
        "margin": -5176,
        "margin_pct": -32.4311,
        "winner": "DEM",
        "color": "#08306b",
        "competitiveness": {
          "color": "#08306b"
        },
        "no_data": false
      },
      "18": {
        "dem_votes": 9634,
        "rep_votes": 8333,
        "other_votes": 0,
        "total_votes": 17967,
        "dem_candidate": "Kristin Collum",
        "rep_candidate": "Janice McGeachin",
        "margin": -1301,
        "margin_pct": -7.2411,
        "winner": "DEM",
        "color": "#6baed6",
        "competitiveness": {
          "color": "#6baed6"
        },
        "no_data": false
      },
      "19": {
        "dem_votes": 10532,
        "rep_votes": 6879,
        "other_votes": 0,
        "total_votes": 17411,
        "dem_candidate": "Kristin Collum",
        "rep_candidate": "Janice McGeachin",
        "margin": -3653,
        "margin_pct": -20.981,
        "winner": "DEM",
        "color": "#08519c",
        "competitiveness": {
          "color": "#08519c"
        },
        "no_data": false
      },
      "20": {
        "dem_votes": 8055,
        "rep_votes": 11201,
        "other_votes": 0,
        "total_votes": 19256,
        "dem_candidate": "Kristin Collum",
        "rep_candidate": "Janice McGeachin",
        "margin": 3146,
        "margin_pct": 16.3378,
        "winner": "REP",
        "color": "#fb6a4a",
        "competitiveness": {
          "color": "#fb6a4a"
        },
        "no_data": false
      },
      "21": {
        "dem_votes": 9388,
        "rep_votes": 11257,
        "other_votes": 0,
        "total_votes": 20645,
        "dem_candidate": "Kristin Collum",
        "rep_candidate": "Janice McGeachin",
        "margin": 1869,
        "margin_pct": 9.053,
        "winner": "REP",
        "color": "#fcae91",
        "competitiveness": {
          "color": "#fcae91"
        },
        "no_data": false
      },
      "22": {
        "dem_votes": 5483,
        "rep_votes": 10223,
        "other_votes": 0,
        "total_votes": 15706,
        "dem_candidate": "Kristin Collum",
        "rep_candidate": "Janice McGeachin",
        "margin": 4740,
        "margin_pct": 30.1795,
        "winner": "REP",
        "color": "#a50f15",
        "competitiveness": {
          "color": "#a50f15"
        },
        "no_data": false
      },
      "23": {
        "dem_votes": 2178,
        "rep_votes": 6099,
        "other_votes": 0,
        "total_votes": 8278,
        "dem_candidate": "Kristin Collum",
        "rep_candidate": "Janice McGeachin",
        "margin": 3921,
        "margin_pct": 47.3665,
        "winner": "REP",
        "color": "#a50f15",
        "competitiveness": {
          "color": "#a50f15"
        },
        "no_data": false
      },
      "24": {
        "dem_votes": 4435,
        "rep_votes": 9705,
        "other_votes": 0,
        "total_votes": 14140,
        "dem_candidate": "Kristin Collum",
        "rep_candidate": "Janice McGeachin",
        "margin": 5270,
        "margin_pct": 37.2702,
        "winner": "REP",
        "color": "#a50f15",
        "competitiveness": {
          "color": "#a50f15"
        },
        "no_data": false
      },
      "25": {
        "dem_votes": 5029,
        "rep_votes": 9884,
        "other_votes": 0,
        "total_votes": 14913,
        "dem_candidate": "Kristin Collum",
        "rep_candidate": "Janice McGeachin",
        "margin": 4855,
        "margin_pct": 32.5555,
        "winner": "REP",
        "color": "#a50f15",
        "competitiveness": {
          "color": "#a50f15"
        },
        "no_data": false
      },
      "26": {
        "dem_votes": 5465,
        "rep_votes": 6665,
        "other_votes": 0,
        "total_votes": 12130,
        "dem_candidate": "Kristin Collum",
        "rep_candidate": "Janice McGeachin",
        "margin": 1200,
        "margin_pct": 9.8928,
        "winner": "REP",
        "color": "#fcae91",
        "competitiveness": {
          "color": "#fcae91"
        },
        "no_data": false
      },
      "27": {
        "dem_votes": 2744,
        "rep_votes": 9996,
        "other_votes": 0,
        "total_votes": 12740,
        "dem_candidate": "Kristin Collum",
        "rep_candidate": "Janice McGeachin",
        "margin": 7252,
        "margin_pct": 56.9231,
        "winner": "REP",
        "color": "#a50f15",
        "competitiveness": {
          "color": "#a50f15"
        },
        "no_data": false
      },
      "28": {
        "dem_votes": 4105,
        "rep_votes": 9372,
        "other_votes": 0,
        "total_votes": 13477,
        "dem_candidate": "Kristin Collum",
        "rep_candidate": "Janice McGeachin",
        "margin": 5267,
        "margin_pct": 39.0814,
        "winner": "REP",
        "color": "#a50f15",
        "competitiveness": {
          "color": "#a50f15"
        },
        "no_data": false
      },
      "29": {
        "dem_votes": 6882,
        "rep_votes": 7000,
        "other_votes": 0,
        "total_votes": 13883,
        "dem_candidate": "Kristin Collum",
        "rep_candidate": "Janice McGeachin",
        "margin": 118,
        "margin_pct": 0.85,
        "winner": "REP",
        "color": "#cbd5e1",
        "competitiveness": {
          "color": "#cbd5e1"
        },
        "no_data": false
      },
      "30": {
        "dem_votes": 3878,
        "rep_votes": 9793,
        "other_votes": 0,
        "total_votes": 13671,
        "dem_candidate": "Kristin Collum",
        "rep_candidate": "Janice McGeachin",
        "margin": 5915,
        "margin_pct": 43.2668,
        "winner": "REP",
        "color": "#a50f15",
        "competitiveness": {
          "color": "#a50f15"
        },
        "no_data": false
      },
      "31": {
        "dem_votes": 3399,
        "rep_votes": 13617,
        "other_votes": 0,
        "total_votes": 17016,
        "dem_candidate": "Kristin Collum",
        "rep_candidate": "Janice McGeachin",
        "margin": 10218,
        "margin_pct": 60.0494,
        "winner": "REP",
        "color": "#a50f15",
        "competitiveness": {
          "color": "#a50f15"
        },
        "no_data": false
      },
      "32": {
        "dem_votes": 1992,
        "rep_votes": 5410,
        "other_votes": 0,
        "total_votes": 7402,
        "dem_candidate": "Kristin Collum",
        "rep_candidate": "Janice McGeachin",
        "margin": 3418,
        "margin_pct": 46.1767,
        "winner": "REP",
        "color": "#a50f15",
        "competitiveness": {
          "color": "#a50f15"
        },
        "no_data": false
      },
      "33": {
        "dem_votes": 5530,
        "rep_votes": 9220,
        "other_votes": 0,
        "total_votes": 14750,
        "dem_candidate": "Kristin Collum",
        "rep_candidate": "Janice McGeachin",
        "margin": 3690,
        "margin_pct": 25.0169,
        "winner": "REP",
        "color": "#de2d26",
        "competitiveness": {
          "color": "#de2d26"
        },
        "no_data": false
      },
      "34": {
        "dem_votes": 1856,
        "rep_votes": 7239,
        "other_votes": 0,
        "total_votes": 9095,
        "dem_candidate": "Kristin Collum",
        "rep_candidate": "Janice McGeachin",
        "margin": 5383,
        "margin_pct": 59.1864,
        "winner": "REP",
        "color": "#a50f15",
        "competitiveness": {
          "color": "#a50f15"
        },
        "no_data": false
      },
      "35": {
        "dem_votes": 5022,
        "rep_votes": 11078,
        "other_votes": 0,
        "total_votes": 16100,
        "dem_candidate": "Kristin Collum",
        "rep_candidate": "Janice McGeachin",
        "margin": 6056,
        "margin_pct": 37.6149,
        "winner": "REP",
        "color": "#a50f15",
        "competitiveness": {
          "color": "#a50f15"
        },
        "no_data": false
      }
    }
  }
}
